LICENSE
MANIFEST.in
NOTICE
README.md
setup.cfg
setup.py
src/phoenics/__init__.py
src/phoenics/__main__.py
src/phoenics/phoenics.py
src/phoenics.egg-info/PKG-INFO
src/phoenics.egg-info/SOURCES.txt
src/phoenics.egg-info/dependency_links.txt
src/phoenics.egg-info/not-zip-safe
src/phoenics.egg-info/requires.txt
src/phoenics.egg-info/top_level.txt
src/phoenics/Acquisition/__init__.py
src/phoenics/Acquisition/acquisition.py
src/phoenics/Acquisition/parameter_optimizer.py
src/phoenics/Acquisition/NumpyOptimizers/__init__.py
src/phoenics/Acquisition/NumpyOptimizers/abstract_optimizer.py
src/phoenics/Acquisition/NumpyOptimizers/adam_optimizer.py
src/phoenics/Acquisition/NumpyOptimizers/__pycache__/__init__.cpython-36.pyc
src/phoenics/Acquisition/NumpyOptimizers/__pycache__/abstract_optimizer.cpython-36.pyc
src/phoenics/Acquisition/NumpyOptimizers/__pycache__/adam_optimizer.cpython-36.pyc
src/phoenics/Acquisition/__pycache__/__init__.cpython-36.pyc
src/phoenics/Acquisition/__pycache__/__init__.cpython-37.pyc
src/phoenics/Acquisition/__pycache__/acquisition.cpython-36.pyc
src/phoenics/Acquisition/__pycache__/acquisition.cpython-37.pyc
src/phoenics/Acquisition/__pycache__/parameter_optimizer.cpython-36.pyc
src/phoenics/Acquisition/__pycache__/parameter_optimizer.cpython-37.pyc
src/phoenics/BayesianNetwork/.bayesian_network.py.swp
src/phoenics/BayesianNetwork/__init__.py
src/phoenics/BayesianNetwork/bayesian_network.py
src/phoenics/BayesianNetwork/kernel_evaluations.c
src/phoenics/BayesianNetwork/kernel_evaluations.cpython-36m-x86_64-linux-gnu.so
src/phoenics/BayesianNetwork/kernel_evaluations.html
src/phoenics/BayesianNetwork/kernel_evaluations.pyx
src/phoenics/BayesianNetwork/kernel_evaluations.pyxbld
src/phoenics/BayesianNetwork/kernel_evaluations.pyxbldc
src/phoenics/BayesianNetwork/model_details.py
src/phoenics/BayesianNetwork/EdwardInterface/__init__.py
src/phoenics/BayesianNetwork/EdwardInterface/edward_interface.py
src/phoenics/BayesianNetwork/EdwardInterface/numpy_graph.py
src/phoenics/BayesianNetwork/EdwardInterface/__pycache__/__init__.cpython-36.pyc
src/phoenics/BayesianNetwork/EdwardInterface/__pycache__/edward_interface.cpython-36.pyc
