Metadata-Version: 2.1
Name: phoenics
Version: 0.1.2b0
Summary: Phoenics: A deep Bayesian optimizer
Home-page: https://github.com/chemos-inc/phoenics
Author: ChemOS Inc.
Author-email: florian@chemos.io
License: Apache license, version 2
Platform: UNKNOWN
Classifier: Intended Audience :: Science/Research
Classifier: Operating System :: Unix
Classifier: Programming Language :: Python
Classifier: Topic :: Scientific/Engineering
Requires-Python: >=3.6
